lwMCMC/__init__.py
lwMCMC/_main.py
lwMCMC-1.0.dist-info/LICENSE
lwMCMC-1.0.dist-info/METADATA
lwMCMC-1.0.dist-info/WHEEL
lwMCMC-1.0.dist-info/top_level.txt
lwMCMC-1.0.dist-info/RECORD
